{"nodes": [{"id": "tests_test_prompt_builder_py", "label": "test_prompt_builder.py", "file_type": "code", "source_file": "tests/test_prompt_builder.py", "source_location": "L1"}, {"id": "test_prompt_builder_test_build_system_prompt", "label": "test_build_system_prompt()", "file_type": "code", "source_file": "tests/test_prompt_builder.py", "source_location": "L8"}, {"id": "test_prompt_builder_test_build_user_prompt", "label": "test_build_user_prompt()", "file_type": "code", "source_file": "tests/test_prompt_builder.py", "source_location": "L17"}, {"id": "test_prompt_builder_test_build_user_prompt_with_questionnaire", "label": "test_build_user_prompt_with_questionnaire()", "file_type": "code", "source_file": "tests/test_prompt_builder.py", "source_location": "L46"}, {"id": "test_prompt_builder_rationale_47", "label": "Verifica que build_user_prompt use el cuestionario din\u00e1mico cuando se le pasa.", "file_type": "rationale", "source_file": "tests/test_prompt_builder.py", "source_location": "L47"}], "edges": [{"source": "tests_test_prompt_builder_py", "target": "types", "relation": "imports", "confidence": "EXTRACTED", "source_file": "tests/test_prompt_builder.py", "source_location": "L1", "weight": 1.0}, {"source": "tests_test_prompt_builder_py", "target": "prompt_builder", "relation": "imports_from", "confidence": "EXTRACTED", "source_file": "tests/test_prompt_builder.py", "source_location": "L3", "weight": 1.0}, {"source": "tests_test_prompt_builder_py", "target": "student_parser", "relation": "imports_from", "confidence": "EXTRACTED", "source_file": "tests/test_prompt_builder.py", "source_location": "L4", "weight": 1.0}, {"source": "tests_test_prompt_builder_py", "target": "variants", "relation": "imports_from", "confidence": "EXTRACTED", "source_file": "tests/test_prompt_builder.py", "source_location": "L5", "weight": 1.0}, {"source": "tests_test_prompt_builder_py", "target": "test_prompt_builder_test_build_system_prompt", "relation": "contains", "confidence": "EXTRACTED", "source_file": "tests/test_prompt_builder.py", "source_location": "L8", "weight": 1.0}, {"source": "tests_test_prompt_builder_py", "target": "test_prompt_builder_test_build_user_prompt", "relation": "contains", "confidence": "EXTRACTED", "source_file": "tests/test_prompt_builder.py", "source_location": "L17", "weight": 1.0}, {"source": "tests_test_prompt_builder_py", "target": "test_prompt_builder_test_build_user_prompt_with_questionnaire", "relation": "contains", "confidence": "EXTRACTED", "source_file": "tests/test_prompt_builder.py", "source_location": "L46", "weight": 1.0}, {"source": "test_prompt_builder_rationale_47", "target": "test_prompt_builder_test_build_user_prompt_with_questionnaire", "relation": "rationale_for", "confidence": "EXTRACTED", "source_file": "tests/test_prompt_builder.py", "source_location": "L47", "weight": 1.0}], "raw_calls": [{"caller_nid": "test_prompt_builder_test_build_system_prompt", "callee": "get_variant_by_id", "source_file": "tests/test_prompt_builder.py", "source_location": "L9"}, {"caller_nid": "test_prompt_builder_test_build_system_prompt", "callee": "build_system_prompt", "source_file": "tests/test_prompt_builder.py", "source_location": "L10"}, {"caller_nid": "test_prompt_builder_test_build_user_prompt", "callee": "Student", "source_file": "tests/test_prompt_builder.py", "source_location": "L18"}, {"caller_nid": "test_prompt_builder_test_build_user_prompt", "callee": "Observation", "source_file": "tests/test_prompt_builder.py", "source_location": "L23"}, {"caller_nid": "test_prompt_builder_test_build_user_prompt", "callee": "get_variant_by_id", "source_file": "tests/test_prompt_builder.py", "source_location": "L35"}, {"caller_nid": "test_prompt_builder_test_build_user_prompt", "callee": "build_user_prompt", "source_file": "tests/test_prompt_builder.py", "source_location": "L36"}, {"caller_nid": "test_prompt_builder_test_build_user_prompt_with_questionnaire", "callee": "Student", "source_file": "tests/test_prompt_builder.py", "source_location": "L48"}, {"caller_nid": "test_prompt_builder_test_build_user_prompt_with_questionnaire", "callee": "get_variant_by_id", "source_file": "tests/test_prompt_builder.py", "source_location": "L63"}, {"caller_nid": "test_prompt_builder_test_build_user_prompt_with_questionnaire", "callee": "SimpleNamespace", "source_file": "tests/test_prompt_builder.py", "source_location": "L65"}, {"caller_nid": "test_prompt_builder_test_build_user_prompt_with_questionnaire", "callee": "SimpleNamespace", "source_file": "tests/test_prompt_builder.py", "source_location": "L67"}, {"caller_nid": "test_prompt_builder_test_build_user_prompt_with_questionnaire", "callee": "SimpleNamespace", "source_file": "tests/test_prompt_builder.py", "source_location": "L73"}, {"caller_nid": "test_prompt_builder_test_build_user_prompt_with_questionnaire", "callee": "SimpleNamespace", "source_file": "tests/test_prompt_builder.py", "source_location": "L79"}, {"caller_nid": "test_prompt_builder_test_build_user_prompt_with_questionnaire", "callee": "SimpleNamespace", "source_file": "tests/test_prompt_builder.py", "source_location": "L85"}, {"caller_nid": "test_prompt_builder_test_build_user_prompt_with_questionnaire", "callee": "SimpleNamespace", "source_file": "tests/test_prompt_builder.py", "source_location": "L91"}, {"caller_nid": "test_prompt_builder_test_build_user_prompt_with_questionnaire", "callee": "SimpleNamespace", "source_file": "tests/test_prompt_builder.py", "source_location": "L97"}, {"caller_nid": "test_prompt_builder_test_build_user_prompt_with_questionnaire", "callee": "SimpleNamespace", "source_file": "tests/test_prompt_builder.py", "source_location": "L103"}, {"caller_nid": "test_prompt_builder_test_build_user_prompt_with_questionnaire", "callee": "SimpleNamespace", "source_file": "tests/test_prompt_builder.py", "source_location": "L109"}, {"caller_nid": "test_prompt_builder_test_build_user_prompt_with_questionnaire", "callee": "build_user_prompt", "source_file": "tests/test_prompt_builder.py", "source_location": "L118"}]}